govtech_csg_xcg/modelpermissions/__init__.py
govtech_csg_xcg/modelpermissions/apps.py
govtech_csg_xcg/modelpermissions/decorators.py
govtech_csg_xcg/modelpermissions/exceptions.py
govtech_csg_xcg/modelpermissions/handlers.py
govtech_csg_xcg/modelpermissions/middleware.py
govtech_csg_xcg/modelpermissions/patch.py
govtech_csg_xcg/modelpermissions/scope.py
govtech_csg_xcg/modelpermissions/shortcuts.py
govtech_csg_xcg/modelpermissions/signals.py
govtech_csg_xcg_modelpermissions-0.1.0.dist-info/LICENSE
govtech_csg_xcg_modelpermissions-0.1.0.dist-info/METADATA
govtech_csg_xcg_modelpermissions-0.1.0.dist-info/WHEEL
govtech_csg_xcg_modelpermissions-0.1.0.dist-info/top_level.txt
govtech_csg_xcg_modelpermissions-0.1.0.dist-info/RECORD
