Metadata-Version: 2.1
Name: govtech-csg-xcg-modelpermissions
Version: 0.1.0
Summary: Package containing functionality related to django model permissions.
Project-URL: Homepage, https://xcg.tech.gov.sg
Project-URL: Documentation, https://xcg.tech.gov.sg
Project-URL: Repository, https://github.com/GovTech-CSG/govtech-csg-xcg-modelpermissions
Classifier: Development Status :: 4 - Beta
Classifier: License :: OSI Approved :: Mozilla Public License 2.0 (MPL 2.0)
Requires-Python: >=3.8
License-File: LICENSE
Requires-Dist: django ~=4.1
Requires-Dist: django-crum
Requires-Dist: django-guardian
